devDocs/__init__.py
devDocs/cli.py
devdocs-0.1.0.dist-info/METADATA
devdocs-0.1.0.dist-info/WHEEL
devdocs-0.1.0.dist-info/entry_points.txt
devdocs-0.1.0.dist-info/top_level.txt
devdocs-0.1.0.dist-info/RECORD
