Metadata-Version: 2.4
Name: devDocs
Version: 0.1.0
Summary: A CLI tool to auto-generate professional README.md files using Google Gemini API.
Author: Gantavya Bansal
Author-email: Gantavya Bansal <gantavyaoo@gmail.com>
License: MIT
Keywords: cli,documentation,readme,generator,gemini-ai
Classifier: Programming Language :: Python :: 3
Classifier: License :: OSI Approved :: MIT License
Classifier: Operating System :: OS Independent
Classifier: Topic :: Documentation
Classifier: Topic :: Software Development :: Code Generators
Requires-Python: >=3.8
Requires-Dist: google-genai
Requires-Dist: httpx
Dynamic: author
Dynamic: requires-python
